[{"id": "e9f56a73045c17a03b03030a26790773", "sport_key": "soccer_uefa_europa_conference_league", "sport_title": "UEFA Europa Conference League", "commence_time": "2023-02-16T17:45:00Z", "home_team": "Qaraba\u011f", "away_team": "AA Gent", "bookmakers": [{"key": "betmgm", "title": "BetMGM", "last_update": "2022-12-27T21:39:21Z", "markets": [{"key": "h2h", "outcomes": [{"name": "AA Gent", "price": 210}, {"name": "Qaraba\u011f", "price": 115}, {"name": "Draw", "price": 250}]}, {"key": "totals", "outcomes": [{"name": "Over", "price": -125, "point": 2.5}, {"name": "Under", "price": -115, "point": 2.5}]}]}, {"key": "draftkings", "title": "DraftKings", "last_update": "2022-12-27T21:38:04Z", "markets": [{"key": "h2h", "outcomes": [{"name": "AA Gent", "price": 230}, {"name": "Qaraba\u011f", "price": 110}, {"name": "Draw", "price": 230}]}]}]}, {"id": "099955889f73d71deedfda643a917d1d", "sport_key": "soccer_uefa_europa_conference_league", "sport_title": "UEFA Europa Conference League", "commence_time": "2023-02-16T17:45:00Z", "home_team": "Trabzonspor", "away_team": "Basel", "bookmakers": [{"key": "betmgm", "title": "BetMGM", "last_update": "2022-12-27T21:39:21Z", "markets": [{"key": "h2h", "outcomes": [{"name": "Basel", "price": 275}, {"name": "Trabzonspor", "price": -110}, {"name": "Draw", "price": 250}]}, {"key": "totals", "outcomes": [{"name": "Over", "price": -120, "point": 2.5}, {"name": "Under", "price": -120, "point": 2.5}]}]}, {"key": "draftkings", "title": "DraftKings", "last_update": "2022-12-27T21:38:04Z", "markets": [{"key": "h2h", "outcomes": [{"name": "Basel", "price": 280}, {"name": "Trabzonspor", "price": -115}, {"name": "Draw", "price": 265}]}]}]}, {"id": "b279db18f59225213f34e1c2fdcde86f", "sport_key": "soccer_uefa_europa_conference_league", "sport_title": "UEFA Europa Conference League", "commence_time": "2023-02-16T17:45:00Z", "home_team": "Braga", "away_team": "Fiorentina", "bookmakers": [{"key": "draftkings", "title": "DraftKings", "last_update": "2022-12-27T21:38:04Z", "markets": [{"key": "h2h", "outcomes": [{"name": "Braga", "price": 150}, {"name": "Fiorentina", "price": 165}, {"name": "Draw", "price": 230}]}]}, {"key": "betmgm", "title": "BetMGM", "last_update": "2022-12-27T21:39:21Z", "markets": [{"key": "h2h", "outcomes": [{"name": "Braga", "price": 140}, {"name": "Fiorentina", "price": 175}, {"name": "Draw", "price": 240}]}, {"key": "totals", "outcomes": [{"name": "Over", "price": -145, "point": 2.5}, {"name": "Under", "price": 100, "point": 2.5}]}]}]}, {"id": "cb6e2a8dd60bcc77965ee54b65109e6b", "sport_key": "soccer_uefa_europa_conference_league", "sport_title": "UEFA Europa Conference League", "commence_time": "2023-02-16T17:45:00Z", "home_team": "FK Bod\u00f8/Glimt", "away_team": "Lech Pozna\u0144", "bookmakers": [{"key": "betmgm", "title": "BetMGM", "last_update": "2022-12-27T21:39:21Z", "markets": [{"key": "h2h", "outcomes": [{"name": "FK Bod\u00f8/Glimt", "price": -145}, {"name": "Lech Pozna\u0144", "price": 340}, {"name": "Draw", "price": 300}]}, {"key": "totals", "outcomes": [{"name": "Over", "price": -160, "point": 2.5}, {"name": "Under", "price": 110, "point": 2.5}]}]}, {"key": "draftkings", "title": "DraftKings", "last_update": "2022-12-27T21:38:04Z", "markets": [{"key": "h2h", "outcomes": [{"name": "FK Bod\u00f8/Glimt", "price": -165}, {"name": "Lech Pozna\u0144", "price": 360}, {"name": "Draw", "price": 320}]}]}]}, {"id": "1107da775ce220e39d6166379e461e8b", "sport_key": "soccer_uefa_europa_conference_league", "sport_title": "UEFA Europa Conference League", "commence_time": "2023-02-16T20:00:00Z", "home_team": "AEK Larnaca", "away_team": "SK Dnipro-1", "bookmakers": [{"key": "betmgm", "title": "BetMGM", "last_update": "2022-12-27T21:39:21Z", "markets": [{"key": "h2h", "outcomes": [{"name": "AEK Larnaca", "price": 145}, {"name": "SK Dnipro-1", "price": 175}, {"name": "Draw", "price": 230}]}, {"key": "totals", "outcomes": [{"name": "Over", "price": -105, "point": 2.5}, {"name": "Under", "price": -135, "point": 2.5}]}]}, {"key": "draftkings", "title": "DraftKings", "last_update": "2022-12-27T21:38:04Z", "markets": [{"key": "h2h", "outcomes": [{"name": "AEK Larnaca", "price": 150}, {"name": "SK Dnipro-1", "price": 180}, {"name": "Draw", "price": 220}]}]}]}, {"id": "046ab3583994a121161a730d8f9e2b91", "sport_key": "soccer_uefa_europa_conference_league", "sport_title": "UEFA Europa Conference League", "commence_time": "2023-02-16T20:00:00Z", "home_team": "Ludogorets", "away_team": "Anderlecht", "bookmakers": [{"key": "draftkings", "title": "DraftKings", "last_update": "2022-12-27T21:38:04Z", "markets": [{"key": "h2h", "outcomes": [{"name": "Anderlecht", "price": 185}, {"name": "Ludogorets", "price": 140}, {"name": "Draw", "price": 220}]}]}, {"key": "betmgm", "title": "BetMGM", "last_update": "2022-12-27T21:39:21Z", "markets": [{"key": "h2h", "outcomes": [{"name": "Anderlecht", "price": 170}, {"name": "Ludogorets", "price": 150}, {"name": "Draw", "price": 230}]}, {"key": "totals", "outcomes": [{"name": "Over", "price": -110, "point": 2.5}, {"name": "Under", "price": -130, "point": 2.5}]}]}]}, {"id": "3f7c0970df0a29eebb937974d882754e", "sport_key": "soccer_uefa_europa_conference_league", "sport_title": "UEFA Europa Conference League", "commence_time": "2023-02-16T20:00:00Z", "home_team": "Lazio", "away_team": "CFR Cluj", "bookmakers": [{"key": "betmgm", "title": "BetMGM", "last_update": "2022-12-27T21:39:21Z", "markets": [{"key": "h2h", "outcomes": [{"name": "CFR Cluj", "price": 625}, {"name": "Lazio", "price": -250}, {"name": "Draw", "price": 350}]}, {"key": "totals", "outcomes": [{"name": "Over", "price": -135, "point": 2.5}, {"name": "Under", "price": -105, "point": 2.5}]}]}, {"key": "draftkings", "title": "DraftKings", "last_update": "2022-12-27T21:38:04Z", "markets": [{"key": "h2h", "outcomes": [{"name": "CFR Cluj", "price": 600}, {"name": "Lazio", "price": -265}, {"name": "Draw", "price": 380}]}]}]}, {"id": "33224a6b72e4c814ad7c568ad0b4b184", "sport_key": "soccer_uefa_europa_conference_league", "sport_title": "UEFA Europa Conference League", "commence_time": "2023-02-16T20:00:00Z", "home_team": "Sheriff Tiraspol", "away_team": "Partizan Belgrade", "bookmakers": [{"key": "betmgm", "title": "BetMGM", "last_update": "2022-12-27T21:39:21Z", "markets": [{"key": "h2h", "outcomes": [{"name": "Partizan Belgrade", "price": 190}, {"name": "Sheriff Tiraspol", "price": 145}, {"name": "Draw", "price": 210}]}, {"key": "totals", "outcomes": [{"name": "Over", "price": -110, "point": 2.5}, {"name": "Under", "price": -130, "point": 2.5}]}]}, {"key": "draftkings", "title": "DraftKings", "last_update": "2022-12-27T21:38:04Z", "markets": [{"key": "h2h", "outcomes": [{"name": "Partizan Belgrade", "price": 180}, {"name": "Sheriff Tiraspol", "price": 155}, {"name": "Draw", "price": 215}]}]}]}]